flask_influxdb/__init__.py
flask_influxdb/flask_influxdb.py
Flask_InfluxDB-0.3.3.dist-info/LICENSE
Flask_InfluxDB-0.3.3.dist-info/METADATA
Flask_InfluxDB-0.3.3.dist-info/WHEEL
Flask_InfluxDB-0.3.3.dist-info/top_level.txt
Flask_InfluxDB-0.3.3.dist-info/RECORD
