Metadata-Version: 2.1
Name: Flask-InfluxDB
Version: 0.3.3
Summary: Flask bindings for the InfluxDB time series database
Home-page: http://github.com/btashton/flask-influxdb
Author: Brennan Ashton
Author-email: brennan@ombitron.com
License: BSD
Platform: any
Classifier: Environment :: Web Environment
Classifier: Intended Audience :: Developers
Classifier: License :: OSI Approved :: BSD License
Classifier: Operating System :: OS Independent
Classifier: Programming Language :: Python
Classifier: Topic :: Internet :: WWW/HTTP :: Dynamic Content
Classifier: Topic :: Software Development :: Libraries :: Python Modules
Requires-Dist: Flask
Requires-Dist: influxdb (>=5.2.0)
